{
  "response": {
    "meta": {
      "hits": 875,
      "time": 32,
      "offset": 50
    },
    "docs": [
      {
        "web_url": "http://www.nytimes.com/reuters/2016/10/19/us/19reuters-new-jersey-bridgegate.html",
        "snippet": "Testimony on Wednesday by Chris Christie's former press secretary added to mounting evidence that the New Jersey governor knew earlier than he has acknowledged that key members of his staff were involved in the \"Bridgegate\" plot to create traffic ...",
        "lead_paragraph": "Testimony on Wednesday by Chris Christie's former press secretary added to mounting evidence that the New Jersey governor knew earlier than he has acknowledged that key members of his staff were involved in the \"Bridgegate\" plot to create traffic gridlock as political payback.",
        "abstract": null,
        "print_page": null,
        "blog": [],
        "source": "Reuters",
        "multimedia": [],
        "headline": {
          "main": "Ex-Christie Spokesman Testifies He Warned Governor on 'Bridgegate'",
          "print_headline": "Ex-Christie Spokesman Testifies He Warned Governor on 'Bridgegate'"
        },
        "keywords": [],
        "pub_date": "2016-10-19T22:15:29Z",
        "document_type": "article",
        "news_desk": null,
        "section_name": "U.S.",
        "subsection_name": null,
        "byline": {
          "person": [],
          "original": "By REUTERS",
          "organization": "REUTERS"
        },
        "type_of_material": "News",
        "_id": "5807f08795d0e022439c420b",
        "word_count": "368",
        "slideshow_credits": null
      },
      {
        "web_url": "http://www.nytimes.com/aponline/2016/10/19/us/ap-la-bus-firetruck-crash.html",
        "snippet": "The unlicensed bus driver involved in an August crash that killed three people and injured dozens in Louisiana has been indicted on three counts of negligent homicide....",
        "lead_paragraph": "The unlicensed bus driver involved in an August crash that killed three people and injured dozens in Louisiana has been indicted on three counts of negligent homicide.",
        "abstract": null,
        "print_page": null,
        "blog": [],
        "source": "AP",
        "multimedia": [],
        "headline": {
          "main": "Unlicensed Bus Driver Indicted in Crash That Killed 3",
          "print_headline": "Unlicensed Bus Driver Indicted in Crash That Killed 3"
        },
        "keywords": [],
        "pub_date": "2016-10-19T22:09:58Z",
        "document_type": "article",
        "news_desk": null,
        "section_name": "U.S.",
        "subsection_name": null,
        "byline": {
          "person": [],
          "original": "By THE ASSOCIATED PRESS",
          "organization": "THE ASSOCIATED PRESS"
        },
        "type_of_material": "News",
        "_id": "5807ef3e95d0e022439c420a",
        "word_count": "135",
        "slideshow_credits": null
      },
      {
        "web_url": "http://www.nytimes.com/aponline/2016/10/19/world/europe/ap-eu-destructive-cyberattacks.html",
        "snippet": "The world should brace itself for more physically destructive hacks, two senior cybersecurity officials said Wednesday, warning that a more dangerous era of hacking was already upon us....",
        "lead_paragraph": "The world should brace itself for more physically destructive hacks, two senior cybersecurity officials said Wednesday, warning that a more dangerous era of hacking was already upon us.",
        "abstract": null,
        "print_page": null,
        "blog": [],
        "source": "AP",
        "multimedia": [],
        "headline": {
          "main": "US, UK Cybersecurity Officials: Destructive Hacks Are Coming",
          "print_headline": "US, UK Cybersecurity Officials: Destructive Hacks Are Coming"
        },
        "keywords": [],
        "pub_date": "2016-10-19T22:07:27Z",
        "document_type": "article",
        "news_desk": null,
        "section_name": "World",
        "subsection_name": "Europe",
        "byline": {
          "person": [],
          "original": "By THE ASSOCIATED PRESS",
          "organization": "THE ASSOCIATED PRESS"
        },
        "type_of_material": "News",
        "_id": "5807eea595d0e022439c4209",
        "word_count": "283",
        "slideshow_credits": null
      },
      {
        "web_url": "http://www.nytimes.com/reuters/2016/10/19/business/19reuters-ecb-policy-decision.html",
        "snippet": "The European Central Bank is set to keep policy unchanged on Thursday but will likely lay the groundwork for more easing in December as it tries to sustain a long-awaited rebound in consumer prices....",
        "lead_paragraph": "The European Central Bank is set to keep policy unchanged on Thursday but will likely lay the groundwork for more easing in December as it tries to sustain a long-awaited rebound in consumer prices.",
        "abstract": null,
        "print_page": null,
        "blog": [],
        "source": "Reuters",
        "multimedia": [],
        "headline": {
          "main": "ECB Seen Firmly on Hold, Charting Course to More Easing in December",
          "print_headline": "ECB Seen Firmly on Hold, Charting Course to More Easing in December"
        },
        "keywords": [],
        "pub_date": "2016-10-19T22:06:28Z",
        "document_type": "article",
        "news_desk": null,
        "section_name": "Business Day",
        "subsection_name": null,
        "byline": {
          "person": [],
          "original": "By REUTERS",
          "organization": "REUTERS"
        },
        "type_of_material": "News",
        "_id": "5807ee6c95d0e022439c4208",
        "word_count": "745",
        "slideshow_credits": null
      },
      {
        "web_url": "http://www.nytimes.com/reuters/2016/10/19/sports/soccer/19reuters-soccer-champions-ars-lud.html",
        "snippet": "Mesut Ozil applied the gloss to a ruthless Arsenal display with a second-half hat-trick in a 6-0 hammering of Ludogorets that put the Gunners on the brink of the Champions League knockout rounds on Wednesday....",
        "lead_paragraph": "Mesut Ozil applied the gloss to a ruthless Arsenal display with a second-half hat-trick in a 6-0 hammering of Ludogorets that put the Gunners on the brink of the Champions League knockout rounds on Wednesday.",
        "abstract": null,
        "print_page": null,
        "blog": [],
        "source": "Reuters",
        "multimedia": [],
        "headline": {
          "main": "Ozil Nets Hat-Trick as Arsenal Thrash Ludogorets 6-0",
          "print_headline": "Ozil Nets Hat-Trick as Arsenal Thrash Ludogorets 6-0"
        },
        "keywords": [],
        "pub_date": "2016-10-19T22:00:31Z",
        "document_type": "article",
        "news_desk": null,
        "section_name": "Sports",
        "subsection_name": "Soccer",
        "byline": {
          "person": [],
          "original": "By REUTERS",
          "organization": "REUTERS"
        },
        "type_of_material": "News",
        "_id": "5807ed0695d0e022439c4207",
        "word_count": "485",
        "slideshow_credits": null
      },
      {
        "web_url": "http://www.nytimes.com/2016/10/20/fashion/coach-jay-z-new-york-shopping-openings-sales.html",
        "snippet": "Shop vintage Moschino dresses, meet the Aquazzura designer at Bergdorf, check out the Gilt City Warehouse Sale and more....",
        "lead_paragraph": "Shop vintage Moschino dresses, meet the Aquazzura designer at Bergdorf, check out the Gilt City Warehouse Sale and more.",
        "abstract": null,
        "print_page": null,
        "blog": [],
        "source": "The New York Times",
        "multimedia": [
          {
            "width": 190,
            "url": "images/2016/10/20/fashion/20SCOUTING-COMBO/20SCOUTING-COMBO-thumbWide.jpg",
            "height": 126,
            "subtype": "wide",
            "legacy": {
              "wide": "images/2016/10/20/fashion/20SCOUTING-COMBO/20SCOUTING-COMBO-thumbWide.jpg",
              "wideheight": "126",
              "widewidth": "190"
            },
            "type": "image"
          },
          {
            "width": 600,
            "url": "images/2016/10/20/fashion/20SCOUTING-COMBO/20SCOUTING-COMBO-articleLarge.jpg",
            "height": 337,
            "subtype": "xlarge",
            "legacy": {
              "xlargewidth": "600",
              "xlarge": "images/2016/10/20/fashion/20SCOUTING-COMBO/20SCOUTING-COMBO-articleLarge.jpg",
              "xlargeheight": "337"
            },
            "type": "image"
          },
          {
            "width": 75,
            "url": "images/2016/10/20/fashion/20SCOUTING-COMBO/20SCOUTING-COMBO-thumbStandard.jpg",
            "height": 75,
            "subtype": "thumbnail",
            "legacy": {
              "thumbnailheight": "75",
              "thumbnail": "images/2016/10/20/fashion/20SCOUTING-COMBO/20SCOUTING-COMBO-thumbStandard.jpg",
              "thumbnailwidth": "75"
            },
            "type": "image"
          }
        ],
        "headline": {
          "main": "Celebrate 75 Years With Coach, 20 Years With Jay Z",
          "content_kicker": "Scouting Report",
          "kicker": "Scouting Report"
        },
        "keywords": [
          {
            "rank": "1",
            "is_major": "N",
            "name": "subject",
            "value": "Fashion and Apparel"
          },
          {
            "rank": "11",
            "is_major": "N",
            "name": "organizations",
            "value": "Away (JRSK Inc)"
          },
          {
            "rank": "2",
            "is_major": "N",
            "name": "subject",
            "value": "Shopping and Retail"
          },
          {
            "rank": "3",
            "is_major": "N",
            "name": "glocations",
            "value": "Manhattan (NYC)"
          },
          {
            "rank": "4",
            "is_major": "N",
            "name": "organizations",
            "value": "Coach Inc"
          },
          {
            "rank": "5",
            "is_major": "N",
            "name": "organizations",
            "value": "Bergdorf Goodman"
          },
          {
            "rank": "6",
            "is_major": "N",
            "name": "organizations",
            "value": "Moschino SpA"
          },
          {
            "rank": "9",
            "is_major": "N",
            "name": "organizations",
            "value": "Joie (Fashion Label)"
          },
          {
            "rank": "10",
            "is_major": "N",
            "name": "organizations",
            "value": "Peruvian Connection (Manhattan, NY, Retailer)"
          }
        ],
        "pub_date": "2016-10-19T21:59:09+0000",
        "document_type": "article",
        "news_desk": "Styles",
        "section_name": "Fashion & Style",
        "subsection_name": null,
        "byline": {
          "person": [
            {
              "firstname": "Alison",
              "middlename": "S.",
              "lastname": "COHN",
              "rank": 1,
              "role": "reported",
              "organization": ""
            }
          ],
          "original": "By ALISON S. COHN"
        },
        "type_of_material": "News",
        "_id": "5807ecb495d0e022439c4206",
        "word_count": "454",
        "slideshow_credits": null
      },
      {
        "web_url": "http://www.nytimes.com/2016/10/19/briefing/presidential-debate-mosul-putin.html",
        "snippet": "Here\u2019s what you need to know at the end of the day....",
        "lead_paragraph": "Here\u2019s what you need to know at the end of the day.",
        "abstract": null,
        "print_page": null,
        "blog": [],
        "source": "The New York Times",
        "multimedia": [
          {
            "width": 190,
            "url": "images/2016/10/19/nytnow/19eveningss-slide-MLPF/19eveningss-slide-MLPF-thumbWide.jpg",
            "height": 126,
            "subtype": "wide",
            "legacy": {
              "wide": "images/2016/10/19/nytnow/19eveningss-slide-MLPF/19eveningss-slide-MLPF-thumbWide.jpg",
              "wideheight": "126",
              "widewidth": "190"
            },
            "type": "image"
          },
          {
            "width": 600,
            "url": "images/2016/10/19/nytnow/19eveningss-slide-MLPF/19eveningss-slide-MLPF-articleLarge.jpg",
            "height": 472,
            "subtype": "xlarge",
            "legacy": {
              "xlargewidth": "600",
              "xlarge": "images/2016/10/19/nytnow/19eveningss-slide-MLPF/19eveningss-slide-MLPF-articleLarge.jpg",
              "xlargeheight": "472"
            },
            "type": "image"
          },
          {
            "width": 75,
            "url": "images/2016/10/19/nytnow/19eveningss-slide-MLPF/19eveningss-slide-MLPF-thumbStandard.jpg",
            "height": 75,
            "subtype": "thumbnail",
            "legacy": {
              "thumbnailheight": "75",
              "thumbnail": "images/2016/10/19/nytnow/19eveningss-slide-MLPF/19eveningss-slide-MLPF-thumbStandard.jpg",
              "thumbnailwidth": "75"
            },
            "type": "image"
          }
        ],
        "headline": {
          "main": "Presidential Debate, Mosul, Putin: Your Wednesday Evening Briefing",
          "print_headline": "Your Evening Briefing"
        },
        "keywords": [],
        "pub_date": "2016-10-19T21:58:38+0000",
        "document_type": "article",
        "news_desk": "NYTNow",
        "section_name": "Briefing",
        "subsection_name": null,
        "byline": {
          "person": [
            {
              "organization": "",
              "role": "reported",
              "firstname": "Karen",
              "rank": 1,
              "lastname": "ZRAICK"
            },
            {
              "organization": "",
              "role": "reported",
              "firstname": "Sandra",
              "rank": 2,
              "lastname": "STEVENSON"
            }
          ],
          "original": "By KAREN ZRAICK and SANDRA STEVENSON"
        },
        "type_of_material": "briefing",
        "_id": "5807eca495d0e022439c4205",
        "word_count": "685",
        "slideshow_credits": null
      },
      {
        "web_url": "http://www.nytimes.com/aponline/2016/10/19/us/ap-us-trump-boyhood-home-auction-the-latest.html",
        "snippet": "The Latest on auction of Donald Trump's boyhood home in New York City. (all times local):...",
        "lead_paragraph": "The Latest on auction of Donald Trump's boyhood home in New York City. (all times local):",
        "abstract": null,
        "print_page": null,
        "blog": [],
        "source": "AP",
        "multimedia": [],
        "headline": {
          "main": "The Latest: Auction of Trump's Boyhood Home Postponed",
          "print_headline": "The Latest: Auction of Trump's Boyhood Home Postponed"
        },
        "keywords": [],
        "pub_date": "2016-10-19T21:57:51Z",
        "document_type": "article",
        "news_desk": null,
        "section_name": "U.S.",
        "subsection_name": null,
        "byline": {
          "person": [],
          "original": "By THE ASSOCIATED PRESS",
          "organization": "THE ASSOCIATED PRESS"
        },
        "type_of_material": "News",
        "_id": "5807ec6595d0e022439c4204",
        "word_count": "230",
        "slideshow_credits": null
      },
      {
        "web_url": "http://www.nytimes.com/2016/10/20/us/politics/hillary-clinton-campaign-slogans.html",
        "snippet": "Buried in the leaked emails of John D. Podesta is a message from August 2015, when the campaign was weighing prospective slogans. Some ring familiar....",
        "lead_paragraph": "Buried in the leaked emails of John D. Podesta is a message from August 2015, when the campaign was weighing prospective slogans. Some ring familiar.",
        "abstract": null,
        "print_page": null,
        "blog": [],
        "source": "The New York Times",
        "multimedia": [
          {
            "width": 190,
            "url": "images/2016/10/20/us/20fd-slogans/20fd-slogans-thumbWide.jpg",
            "height": 126,
            "subtype": "wide",
            "legacy": {
              "wide": "images/2016/10/20/us/20fd-slogans/20fd-slogans-thumbWide.jpg",
              "wideheight": "126",
              "widewidth": "190"
            },
            "type": "image"
          },
          {
            "width": 600,
            "url": "images/2016/10/20/us/20fd-slogans/20fd-slogans-articleLarge.jpg",
            "height": 400,
            "subtype": "xlarge",
            "legacy": {
              "xlargewidth": "600",
              "xlarge": "images/2016/10/20/us/20fd-slogans/20fd-slogans-articleLarge.jpg",
              "xlargeheight": "400"
            },
            "type": "image"
          },
          {
            "width": 75,
            "url": "images/2016/10/20/us/20fd-slogans/20fd-slogans-thumbStandard.jpg",
            "height": 75,
            "subtype": "thumbnail",
            "legacy": {
              "thumbnailheight": "75",
              "thumbnail": "images/2016/10/20/us/20fd-slogans/20fd-slogans-thumbStandard.jpg",
              "thumbnailwidth": "75"
            },
            "type": "image"
          }
        ],
        "headline": {
          "main": "When Hillary Clinton Tested New Slogans \u2014 85 of Them"
        },
        "keywords": [
          {
            "rank": "1",
            "is_major": "N",
            "name": "subject",
            "value": "Presidential Election of 2016"
          },
          {
            "rank": "2",
            "is_major": "N",
            "name": "persons",
            "value": "Clinton, Hillary Rodham"
          },
          {
            "rank": "3",
            "is_major": "N",
            "name": "subject",
            "value": "Slogans and Mottoes"
          },
          {
            "rank": "4",
            "is_major": "N",
            "name": "persons",
            "value": "Podesta, John D"
          }
        ],
        "pub_date": "2016-10-19T21:56:02+0000",
        "document_type": "article",
        "news_desk": "National",
        "section_name": "U.S.",
        "subsection_name": "Politics",
        "byline": {
          "person": [
            {
              "organization": "",
              "role": "reported",
              "firstname": "Matt",
              "rank": 1,
              "lastname": "FLEGENHEIMER"
            }
          ],
          "original": "By MATT FLEGENHEIMER"
        },
        "type_of_material": "News",
        "_id": "5807ebf595d0e022439c4203",
        "word_count": "669",
        "slideshow_credits": null
      },
      {
        "web_url": "http://www.nytimes.com/aponline/2016/10/19/us/ap-us-wells-fargo-california.html",
        "snippet": "California's attorney general is conducting a criminal investigation into whether employees at San Francisco-based Wells Fargo bank stole customers' identities in the sales practices scandal that rocked the bank and cost its CEO his job, documents...",
        "lead_paragraph": "California's attorney general is conducting a criminal investigation into whether employees at San Francisco-based Wells Fargo bank stole customers' identities in the sales practices scandal that rocked the bank and cost its CEO his job, documents released Wednesday show.",
        "abstract": null,
        "print_page": null,
        "blog": [],
        "source": "AP",
        "multimedia": [],
        "headline": {
          "main": "Attorney General Leads Criminal Probe of Wells Fargo Bank",
          "print_headline": "Attorney General Leads Criminal Probe of Wells Fargo Bank"
        },
        "keywords": [],
        "pub_date": "2016-10-19T21:55:03Z",
        "document_type": "article",
        "news_desk": null,
        "section_name": "U.S.",
        "subsection_name": null,
        "byline": {
          "person": [],
          "original": "By THE ASSOCIATED PRESS",
          "organization": "THE ASSOCIATED PRESS"
        },
        "type_of_material": "News",
        "_id": "5807ebbf95d0e022439c4202",
        "word_count": "658",
        "slideshow_credits": null
      }
    ]
  },
  "status": "OK",
  "copyright": "Copyright (c) 2013 The New York Times Company.  All Rights Reserved."
}