{
  "response": {
    "meta": {
      "hits": 837,
      "time": 70,
      "offset": 50
    },
    "docs": [
      {
        "web_url": "http://www.nytimes.com/reuters/2016/10/11/sports/hockey/11reuters-nhl-preview.html",
        "snippet": "The puck drops on the National Hockey League's 2016-17 season on Wednesday and some teams could race out of the gate playing at a higher level than usual with many players fresh off competing in the World Cup of Hockey....",
        "lead_paragraph": "The puck drops on the National Hockey League's 2016-17 season on Wednesday and some teams could race out of the gate playing at a higher level than usual with many players fresh off competing in the World Cup of Hockey.",
        "abstract": null,
        "print_page": null,
        "blog": [],
        "source": "Reuters",
        "multimedia": [],
        "headline": {
          "main": "NHL: All Eyes on Crosby's Penguins as Puck Drops on New Season",
          "print_headline": "NHL: All Eyes on Crosby's Penguins as Puck Drops on New Season"
        },
        "keywords": [],
        "pub_date": "2016-10-11T21:39:25Z",
        "document_type": "article",
        "news_desk": null,
        "section_name": "Sports",
        "subsection_name": "Hockey",
        "byline": {
          "person": [],
          "original": "By REUTERS",
          "organization": "REUTERS"
        },
        "type_of_material": "News",
        "_id": "57fd5d2495d0e022439c2a2d",
        "word_count": "397",
        "slideshow_credits": null
      },
      {
        "web_url": "http://www.nytimes.com/reuters/2016/10/11/business/11reuters-walmart-managers-overtime.html",
        "snippet": "Wal-Mart Stores Inc has raised salaries for entry-level managers before a rule change that extends mandatory overtime pay to more than 4 million U.S. workers, in an attempt to shield itself from unpredictable additional costs for salaried employee...",
        "lead_paragraph": "Wal-Mart Stores Inc has raised salaries for entry-level managers before a rule change that extends mandatory overtime pay to more than 4 million U.S. workers, in an attempt to shield itself from unpredictable additional costs for salaried employees. ",
        "abstract": null,
        "print_page": null,
        "blog": [],
        "source": "Reuters",
        "multimedia": [],
        "headline": {
          "main": "Wal-Mart Ups Entry-Level Manager Salaries Ahead of Overtime Rule",
          "print_headline": "Wal-Mart Ups Entry-Level Manager Salaries Ahead of Overtime Rule"
        },
        "keywords": [],
        "pub_date": "2016-10-11T21:36:44Z",
        "document_type": "article",
        "news_desk": null,
        "section_name": "Business Day",
        "subsection_name": null,
        "byline": {
          "person": [],
          "original": "By REUTERS",
          "organization": "REUTERS"
        },
        "type_of_material": "News",
        "_id": "57fd5d6495d0e022439c2a34",
        "word_count": "393",
        "slideshow_credits": null
      },
      {
        "web_url": "http://www.nytimes.com/aponline/2016/10/11/us/ap-me-trump-maine-governor.html",
        "snippet": "Republican Maine Gov. Paul LePage says the country needs Donald Trump \"to show some authoritarian power in our country\" because Democratic President Barack Obama has acted like \"an autocrat\" during his tenure as president....",
        "lead_paragraph": "Republican Maine Gov. Paul LePage says the country needs Donald Trump \"to show some authoritarian power in our country\" because Democratic President Barack Obama has acted like \"an autocrat\" during his tenure as president.",
        "abstract": null,
        "print_page": null,
        "blog": [],
        "source": "AP",
        "multimedia": [],
        "headline": {
          "main": "Maine Governor: Trump Can Bring Needed 'Authoritarian' Power",
          "print_headline": "Maine Governor: Trump Can Bring Needed 'Authoritarian' Power"
        },
        "keywords": [],
        "pub_date": "2016-10-11T21:35:05Z",
        "document_type": "article",
        "news_desk": null,
        "section_name": "U.S.",
        "subsection_name": null,
        "byline": {
          "person": [],
          "original": "By THE ASSOCIATED PRESS",
          "organization": "THE ASSOCIATED PRESS"
        },
        "type_of_material": "News",
        "_id": "57fd5d5b95d0e022439c2a32",
        "word_count": "200",
        "slideshow_credits": null
      },
      {
        "web_url": "http://www.nytimes.com/reuters/2016/10/11/sports/soccer/11reuters-soccer-worldcup-slo-eng.html",
        "snippet": "England were indebted to inspired keeper Joe Hart as they stumbled to a 0-0 draw in Slovenia in World Cup qualifying Group F on Tuesday -- a result which ended their 14-game winning sequence in qualifying matches....",
        "lead_paragraph": "England were indebted to inspired keeper Joe Hart as they stumbled to a 0-0 draw in Slovenia in World Cup qualifying Group F on Tuesday -- a result which ended their 14-game winning sequence in qualifying matches.",
        "abstract": null,
        "print_page": null,
        "blog": [],
        "source": "Reuters",
        "multimedia": [],
        "headline": {
          "main": "Inspired Hart Earns Sloppy England a Point in Slovenia",
          "print_headline": "Inspired Hart Earns Sloppy England a Point in Slovenia"
        },
        "keywords": [],
        "pub_date": "2016-10-11T21:35:20Z",
        "document_type": "article",
        "news_desk": null,
        "section_name": "Sports",
        "subsection_name": "Soccer",
        "byline": {
          "person": [],
          "original": "By REUTERS",
          "organization": "REUTERS"
        },
        "type_of_material": "News",
        "_id": "57fd5cd495d0e022439c2a28",
        "word_count": "540",
        "slideshow_credits": null
      },
      {
        "web_url": "http://www.nytimes.com/reuters/2016/10/11/sports/soccer/11reuters-soccer-worldcup-ger-nir.html",
        "snippet": "World champions Germany struck twice in four first-half minutes to beat Northern Ireland 2-0 in their 2018 World Cup qualifier on Tuesday and stretch their winning run in Group C with their best ever start in a tournament qualification....",
        "lead_paragraph": "World champions Germany struck twice in four first-half minutes to beat Northern Ireland 2-0 in their 2018 World Cup qualifier on Tuesday and stretch their winning run in Group C with their best ever start in a tournament qualification.",
        "abstract": null,
        "print_page": null,
        "blog": [],
        "source": "Reuters",
        "multimedia": [],
        "headline": {
          "main": "Germany Cruise to 2-0 Win Over Northern Ireland",
          "print_headline": "Germany Cruise to 2-0 Win Over Northern Ireland"
        },
        "keywords": [],
        "pub_date": "2016-10-11T21:32:26Z",
        "document_type": "article",
        "news_desk": null,
        "section_name": "Sports",
        "subsection_name": "Soccer",
        "byline": {
          "person": [],
          "original": "By REUTERS",
          "organization": "REUTERS"
        },
        "type_of_material": "News",
        "_id": "57fd5d4695d0e022439c2a31",
        "word_count": "403",
        "slideshow_credits": null
      },
      {
        "web_url": "http://www.nytimes.com/aponline/2016/10/11/sports/golf/ap-glf-on-the-fringe-tiger-woods.html",
        "snippet": "The Tiger comeback has become the Tiger tease....",
        "lead_paragraph": "The Tiger comeback has become the Tiger tease.",
        "abstract": null,
        "print_page": null,
        "blog": [],
        "source": "AP",
        "multimedia": [],
        "headline": {
          "main": "Column: The Tiger Comeback Becomes the Tiger Tease",
          "print_headline": "Column: The Tiger Comeback Becomes the Tiger Tease"
        },
        "keywords": [],
        "pub_date": "2016-10-11T21:24:53Z",
        "document_type": "article",
        "news_desk": null,
        "section_name": "Sports",
        "subsection_name": "Golf",
        "byline": {
          "person": [],
          "original": "By THE ASSOCIATED PRESS",
          "organization": "THE ASSOCIATED PRESS"
        },
        "type_of_material": "News",
        "_id": "57fd5d3a95d0e022439c2a30",
        "word_count": "776",
        "slideshow_credits": null
      },
      {
        "web_url": "http://www.nytimes.com/reuters/2016/10/11/business/11reuters-facebook-sandberg.html",
        "snippet": "Facebook Inc Chief Operating Officer Sheryl Sandberg, who has been mentioned as a potential Treasury Secretary should Democrat Hillary Clinton become the next U.S. president, said on Tuesday she has no plans to go into government....",
        "lead_paragraph": "Facebook Inc Chief Operating Officer Sheryl Sandberg, who has been mentioned as a potential Treasury Secretary should Democrat Hillary Clinton become the next U.S. president, said on Tuesday she has no plans to go into government.",
        "abstract": null,
        "print_page": null,
        "blog": [],
        "source": "Reuters",
        "multimedia": [],
        "headline": {
          "main": "Facebook's Sandberg Says Has No Plan to Work in Government",
          "print_headline": "Facebook's Sandberg Says Has No Plan to Work in Government"
        },
        "keywords": [],
        "pub_date": "2016-10-11T21:26:02Z",
        "document_type": "article",
        "news_desk": null,
        "section_name": "Business Day",
        "subsection_name": null,
        "byline": {
          "person": [],
          "original": "By REUTERS",
          "organization": "REUTERS"
        },
        "type_of_material": "News",
        "_id": "57fd5d1b95d0e022439c2a2b",
        "word_count": "79",
        "slideshow_credits": null
      },
      {
        "web_url": "http://www.nytimes.com/aponline/2016/10/11/us/ap-us-fallen-firefighters.html",
        "snippet": "The names of eight New York firefighters who died in the line of duty have been added to a memorial near the state Capitol....",
        "lead_paragraph": "The names of eight New York firefighters who died in the line of duty have been added to a memorial near the state Capitol.",
        "abstract": null,
        "print_page": null,
        "blog": [],
        "source": "AP",
        "multimedia": [],
        "headline": {
          "main": "Names of 8 Fallen Firefighters Added to NY Memorial Wall",
          "print_headline": "Names of 8 Fallen Firefighters Added to NY Memorial Wall"
        },
        "keywords": [],
        "pub_date": "2016-10-11T20:34:06Z",
        "document_type": "article",
        "news_desk": null,
        "section_name": "U.S.",
        "subsection_name": null,
        "byline": {
          "person": [],
          "original": "By THE ASSOCIATED PRESS",
          "organization": "THE ASSOCIATED PRESS"
        },
        "type_of_material": "News",
        "_id": "57fd5c4b95d0e022439c2a25",
        "word_count": "132",
        "slideshow_credits": null
      },
      {
        "web_url": "http://www.nytimes.com/aponline/2016/10/11/us/ap-financial-markets-box.html",
        "snippet": "Stocks closed broadly lower Tuesday, more than erasing the previous day's gain....",
        "lead_paragraph": "Stocks closed broadly lower Tuesday, more than erasing the previous day's gain.",
        "abstract": null,
        "print_page": null,
        "blog": [],
        "source": "AP",
        "multimedia": [],
        "headline": {
          "main": "How the Dow Jones Industrial Average Fared on Tuesday",
          "print_headline": "How the Dow Jones Industrial Average Fared on Tuesday"
        },
        "keywords": [],
        "pub_date": "2016-10-11T21:16:53Z",
        "document_type": "article",
        "news_desk": null,
        "section_name": "U.S.",
        "subsection_name": null,
        "byline": {
          "person": [],
          "original": "By THE ASSOCIATED PRESS",
          "organization": "THE ASSOCIATED PRESS"
        },
        "type_of_material": "News",
        "_id": "57fd5cee95d0e022439c2a29",
        "word_count": "144",
        "slideshow_credits": null
      },
      {
        "web_url": "http://news.blogs.nytimes.com/2016/10/11/what-were-reading-196/",
        "snippet": "Get recommendations from New York Times reporters and editors, highlighting great stories from around the web. Today, great reads from John Schwartz, Tyson Evans and others....",
        "lead_paragraph": null,
        "abstract": "Get recommendations from New York Times reporters and editors, highlighting great stories from around the web. Today, great reads from John Schwartz, Tyson Evans and others.",
        "print_page": null,
        "blog": [],
        "source": "The New York Times",
        "multimedia": [
          {
            "width": 190,
            "url": "images/2016/10/11/nytnow/11wwr1/11wwr1-thumbWide.jpg",
            "height": 126,
            "subtype": "wide",
            "legacy": {
              "wide": "images/2016/10/11/nytnow/11wwr1/11wwr1-thumbWide.jpg",
              "wideheight": "126",
              "widewidth": "190"
            },
            "type": "image"
          },
          {
            "width": 75,
            "url": "images/2016/10/11/nytnow/11wwr1/11wwr1-thumbStandard.jpg",
            "height": 75,
            "subtype": "thumbnail",
            "legacy": {
              "thumbnailheight": "75",
              "thumbnail": "images/2016/10/11/nytnow/11wwr1/11wwr1-thumbStandard.jpg",
              "thumbnailwidth": "75"
            },
            "type": "image"
          }
        ],
        "headline": {
          "main": "What We&#8217;re Reading",
          "kicker": "News"
        },
        "keywords": [
          {
            "rank": "1",
            "name": "persons",
            "value": "Richardson, Lynda"
          },
          {
            "rank": "2",
            "name": "persons",
            "value": "Schwartz, John"
          },
          {
            "rank": "1",
            "name": "organizations",
            "value": "Time (Magazine)"
          }
        ],
        "pub_date": "2016-10-11T21:14:08Z",
        "document_type": "blogpost",
        "news_desk": null,
        "section_name": "Blogs",
        "subsection_name": null,
        "byline": {
          "person": [],
          "original": "By THE NEW YORK TIMES",
          "organization": "The New York Times"
        },
        "type_of_material": "Blog",
        "_id": "57fd5c2b95d0e022439c2a24",
        "word_count": "342",
        "slideshow_credits": null
      }
    ]
  },
  "status": "OK",
  "copyright": "Copyright (c) 2013 The New York Times Company.  All Rights Reserved."
}