{
  "response": {
    "meta": {
      "hits": 548,
      "time": 69,
      "offset": 10
    },
    "docs": [
      {
        "web_url": "http://www.nytimes.com/aponline/2016/07/04/world/asia/ap-as-indonesia-suicide-bomber.html",
        "snippet": "Indonesian police said the militant who died in a suicide bombing Tuesday outside police headquarters in the city of Solo was linked to a leading figure among the Indonesian radicals with the Islamic State group in Syria....",
        "lead_paragraph": "Indonesian police said the militant who died in a suicide bombing Tuesday outside police headquarters in the city of Solo was linked to a leading figure among the Indonesian radicals with the Islamic State group in Syria.",
        "abstract": null,
        "print_page": null,
        "blog": [],
        "source": "AP",
        "multimedia": [],
        "headline": {
          "main": "Suspected Militant Dies in Indonesia Suicide Bombing",
          "print_headline": "Suspected Militant Dies in Indonesia Suicide Bombing"
        },
        "keywords": [],
        "pub_date": "2016-07-04T22:29:30Z",
        "document_type": "article",
        "news_desk": "None",
        "section_name": "World",
        "subsection_name": "Asia Pacific",
        "byline": {
          "person": [],
          "original": "By THE ASSOCIATED PRESS",
          "organization": "THE ASSOCIATED PRESS"
        },
        "type_of_material": "News",
        "_id": "577b1bcf38f0d83e1f65d725",
        "word_count": "391",
        "slideshow_credits": null
      },
      {
        "web_url": "http://www.nytimes.com/aponline/2016/07/04/sports/baseball/ap-bbn-mets-reyes.html",
        "snippet": "Jose Reyes is set to rejoin the New York Mets for Tuesday night's game against the Miami Marlins, his return to the major leagues following a domestic violence suspension....",
        "lead_paragraph": "Jose Reyes is set to rejoin the New York Mets for Tuesday night's game against the Miami Marlins, his return to the major leagues following a domestic violence suspension.",
        "abstract": null,
        "print_page": null,
        "blog": [],
        "source": "AP",
        "multimedia": [],
        "headline": {
          "main": "Mets Plan to Bring Up Jose Reyes on Tuesday",
          "print_headline": "Mets Plan to Bring Up Jose Reyes on Tuesday"
        },
        "keywords": [],
        "pub_date": "2016-07-04T22:25:00Z",
        "document_type": "article",
        "news_desk": "None",
        "section_name": "Sports",
        "subsection_name": "Baseball",
        "byline": {
          "person": [],
          "original": "By THE ASSOCIATED PRESS",
          "organization": "THE ASSOCIATED PRESS"
        },
        "type_of_material": "News",
        "_id": "577b1b2438f0d83e1f65d724",
        "word_count": "370",
        "slideshow_credits": null
      },
      {
        "web_url": "http://www.nytimes.com/reuters/2016/07/04/business/04reuters-china-economy-pmi-services-caixin.html",
        "snippet": "Activity in China's services sector rose to an 11-month high in June, a private survey showed on Tuesday, diverging from struggling manufacturing in a trend that if sustainable would indicate Beijing is making progress in rebalancing the economy....",
        "lead_paragraph": "Activity in China's services sector rose to an 11-month high in June, a private survey showed on Tuesday, diverging from struggling manufacturing in a trend that if sustainable would indicate Beijing is making progress in rebalancing the economy. ",
        "abstract": null,
        "print_page": null,
        "blog": [],
        "source": "Reuters",
        "multimedia": [],
        "headline": {
          "main": "China Service Sector Activity Jumps to 11-Month High-Caixin PMI",
          "print_headline": "China Service Sector Activity Jumps to 11-Month High-Caixin PMI"
        },
        "keywords": [],
        "pub_date": "2016-07-04T22:21:29Z",
        "document_type": "article",
        "news_desk": "None",
        "section_name": "Business Day",
        "subsection_name": null,
        "byline": {
          "person": [],
          "original": "By REUTERS",
          "organization": "REUTERS"
        },
        "type_of_material": "News",
        "_id": "577b1a6938f0d83e1f65d723",
        "word_count": "436",
        "slideshow_credits": null
      },
      {
        "web_url": "http://www.nytimes.com/reuters/2016/07/04/world/asia/04reuters-indonesia-security.html",
        "snippet": "A suicide bomber on a motorcycle attacked a police station in the small Indonesian city of Solo on Tuesday, killing himself and wounding a police officer, a police spokesman said....",
        "lead_paragraph": "A suicide bomber on a motorcycle attacked a police station in the small Indonesian city of Solo on Tuesday, killing himself and wounding a police officer, a police spokesman said.",
        "abstract": null,
        "print_page": null,
        "blog": [],
        "source": "Reuters",
        "multimedia": [],
        "headline": {
          "main": "Suicide Bomber Attacks Indonesian Police Station, Wounding One",
          "print_headline": "Suicide Bomber Attacks Indonesian Police Station, Wounding One"
        },
        "keywords": [],
        "pub_date": "2016-07-04T22:16:51Z",
        "document_type": "article",
        "news_desk": "None",
        "section_name": "World",
        "subsection_name": "Asia Pacific",
        "byline": {
          "person": [],
          "original": "By REUTERS",
          "organization": "REUTERS"
        },
        "type_of_material": "News",
        "_id": "577b18f738f0d83e1f65d722",
        "word_count": "343",
        "slideshow_credits": null
      },
      {
        "web_url": "http://www.nytimes.com/reuters/2016/07/04/world/asia/04reuters-southchinasea-china.html",
        "snippet": "China should prepare itself for military confrontation in the South China Sea, an influential Chinese paper said on Tuesday, a week ahead of a decision by an international court on a dispute there between China and the Philippines....",
        "lead_paragraph": "China should prepare itself for military confrontation in the South China Sea, an influential Chinese paper said on Tuesday, a week ahead of a decision by an international court on a dispute there between China and the Philippines.",
        "abstract": null,
        "print_page": null,
        "blog": [],
        "source": "Reuters",
        "multimedia": [],
        "headline": {
          "main": "Chinese Paper Says Should Prepare for South China Sea Armed Clash",
          "print_headline": "Chinese Paper Says Should Prepare for South China Sea Armed Clash"
        },
        "keywords": [],
        "pub_date": "2016-07-04T22:12:54Z",
        "document_type": "article",
        "news_desk": "None",
        "section_name": "World",
        "subsection_name": "Asia Pacific",
        "byline": {
          "person": [],
          "original": "By REUTERS",
          "organization": "REUTERS"
        },
        "type_of_material": "News",
        "_id": "577b184538f0d83e1f65d721",
        "word_count": "426",
        "slideshow_credits": null
      },
      {
        "web_url": "http://www.nytimes.com/reuters/2016/07/04/us/politics/04reuters-usa-election-trump-ernst.html",
        "snippet": "Presumptive Republican presidential nominee Donald Trump met with U.S. Senator Joni Ernst of Iowa on Monday, feeding speculation she could be on the short list for consideration as his vice presidential running mate, Fox News reported....",
        "lead_paragraph": "Presumptive Republican presidential nominee Donald Trump met with U.S. Senator Joni Ernst of Iowa on Monday, feeding speculation she could be on the short list for consideration as his vice presidential running mate, Fox News reported.",
        "abstract": null,
        "print_page": null,
        "blog": [],
        "source": "Reuters",
        "multimedia": [],
        "headline": {
          "main": "Trump Meets Senator Ernst Amid Vice Presidential Speculation",
          "print_headline": "Trump Meets Senator Ernst Amid Vice Presidential Speculation"
        },
        "keywords": [],
        "pub_date": "2016-07-04T22:04:16Z",
        "document_type": "article",
        "news_desk": "None",
        "section_name": "U.S.",
        "subsection_name": "Politics",
        "byline": {
          "person": [],
          "original": "By REUTERS",
          "organization": "REUTERS"
        },
        "type_of_material": "News",
        "_id": "577b162a38f0d83e1f65d71f",
        "word_count": "189",
        "slideshow_credits": null
      },
      {
        "web_url": "http://wordplay.blogs.nytimes.com/2016/07/04/pirates-guide/",
        "snippet": "Jules Markey uncovers something important....",
        "lead_paragraph": null,
        "abstract": "Jules Markey uncovers something important.",
        "print_page": null,
        "blog": [],
        "source": "The New York Times",
        "multimedia": [
          {
            "width": 190,
            "url": "images/2016/07/04/crosswords/05wordplaycoins/05wordplaycoins-thumbWide.jpg",
            "height": 126,
            "subtype": "wide",
            "legacy": {
              "wide": "images/2016/07/04/crosswords/05wordplaycoins/05wordplaycoins-thumbWide.jpg",
              "wideheight": "126",
              "widewidth": "190"
            },
            "type": "image"
          },
          {
            "width": 600,
            "url": "images/2016/07/04/crosswords/05wordplaycoins/05wordplaycoins-articleLarge.jpg",
            "height": 418,
            "subtype": "xlarge",
            "legacy": {
              "xlargewidth": "600",
              "xlarge": "images/2016/07/04/crosswords/05wordplaycoins/05wordplaycoins-articleLarge.jpg",
              "xlargeheight": "418"
            },
            "type": "image"
          },
          {
            "width": 75,
            "url": "images/2016/07/04/crosswords/05wordplaycoins/05wordplaycoins-thumbStandard.jpg",
            "height": 75,
            "subtype": "thumbnail",
            "legacy": {
              "thumbnailheight": "75",
              "thumbnail": "images/2016/07/04/crosswords/05wordplaycoins/05wordplaycoins-thumbStandard.jpg",
              "thumbnailwidth": "75"
            },
            "type": "image"
          }
        ],
        "headline": {
          "main": "Pirate&#8217;s Guide",
          "kicker": "Wordplay"
        },
        "keywords": [
          {
            "rank": "1",
            "name": "subject",
            "value": "Crossword Puzzles"
          }
        ],
        "pub_date": "2016-07-04T22:00:40Z",
        "document_type": "blogpost",
        "news_desk": "Business",
        "section_name": "Crosswords & Games",
        "subsection_name": null,
        "byline": {
          "person": [
            {
              "organization": "",
              "role": "reported",
              "firstname": "Deb",
              "rank": 1,
              "lastname": "AMLEN"
            }
          ],
          "original": "By DEB AMLEN"
        },
        "type_of_material": "Blog",
        "_id": "577b155b38f0d83e1f65d71e",
        "word_count": "496",
        "slideshow_credits": null
      },
      {
        "web_url": "http://www.nytimes.com/aponline/2016/07/04/sports/olympics/ap-oly-ath-us-track-trials.html",
        "snippet": "The first thing Alysia Montano thought was, \"Get up. Get up.\"...",
        "lead_paragraph": "The first thing Alysia Montano thought was, \"Get up. Get up.\"",
        "abstract": null,
        "print_page": null,
        "blog": [],
        "source": "AP",
        "multimedia": [],
        "headline": {
          "main": "Montano Suffers a Different Setback at Trials",
          "print_headline": "Montano Suffers a Different Setback at Trials"
        },
        "keywords": [],
        "pub_date": "2016-07-04T21:33:25Z",
        "document_type": "article",
        "news_desk": "None",
        "section_name": "Sports",
        "subsection_name": "Olympics",
        "byline": {
          "person": [],
          "original": "By THE ASSOCIATED PRESS",
          "organization": "THE ASSOCIATED PRESS"
        },
        "type_of_material": "News",
        "_id": "577b0f2f38f0d83e1f65d71c",
        "word_count": "897",
        "slideshow_credits": null
      },
      {
        "web_url": "http://www.nytimes.com/aponline/2016/07/04/us/ap-10-things-to-know-tuesday.html",
        "snippet": "Your daily look at late-breaking news, upcoming events and the stories that will be talked about Tuesday:...",
        "lead_paragraph": "Your daily look at late-breaking news, upcoming events and the stories that will be talked about Tuesday:",
        "abstract": null,
        "print_page": null,
        "blog": [],
        "source": "AP",
        "multimedia": [],
        "headline": {
          "main": "10 Things to Know for Tuesday",
          "print_headline": "10 Things to Know for Tuesday"
        },
        "keywords": [],
        "pub_date": "2016-07-04T21:34:01Z",
        "document_type": "article",
        "news_desk": "None",
        "section_name": "U.S.",
        "subsection_name": null,
        "byline": {
          "person": [],
          "original": "By THE ASSOCIATED PRESS",
          "organization": "THE ASSOCIATED PRESS"
        },
        "type_of_material": "News",
        "_id": "577b0f2a38f0d83e1f65d71b",
        "word_count": "394",
        "slideshow_credits": null
      },
      {
        "web_url": "http://www.nytimes.com/aponline/2016/07/04/us/ap-us-missing-boat.html",
        "snippet": "The U.S. Coast Guard on Monday continued searching for three missing fishermen off Hawaii after search and rescue crews found their overturned boat....",
        "lead_paragraph": "The U.S. Coast Guard on Monday continued searching for three missing fishermen off Hawaii after search and rescue crews found their overturned boat.",
        "abstract": null,
        "print_page": null,
        "blog": [],
        "source": "AP",
        "multimedia": [],
        "headline": {
          "main": "Coast Guard Searching for 3 Fishermen Missing Off Hawaii",
          "print_headline": "Coast Guard Searching for 3 Fishermen Missing Off Hawaii"
        },
        "keywords": [],
        "pub_date": "2016-07-04T21:29:50Z",
        "document_type": "article",
        "news_desk": "None",
        "section_name": "U.S.",
        "subsection_name": null,
        "byline": {
          "person": [],
          "original": "By THE ASSOCIATED PRESS",
          "organization": "THE ASSOCIATED PRESS"
        },
        "type_of_material": "News",
        "_id": "577b0e7338f0d83e1f65d71a",
        "word_count": "125",
        "slideshow_credits": null
      }
    ]
  },
  "status": "OK",
  "copyright": "Copyright (c) 2013 The New York Times Company.  All Rights Reserved."
}